pyspeller.py
pyspeller-1.0.0.dist-info/METADATA
pyspeller-1.0.0.dist-info/WHEEL
pyspeller-1.0.0.dist-info/licenses/LICENSE
pyspeller-1.0.0.dist-info/RECORD
