Metadata-Version: 2.4
Name: pyspeller
Version: 1.0.0
Summary: Библиотека для проверки орфографии с использованием API Яндекс Спеллер. Обертка Python для Яндекс.Спеллер.
Project-URL: Repository, https://github.com/austnv/pyspeller
Project-URL: Issues, https://github.com/austnv/pyspeller/issues
Project-URL: Homepage, https://github.com/austnv/pyspeller
Project-URL: Changelog, https://github.com/austnv/pyspeller/releases
Project-URL: Documentation, https://github.com/austnv/pyspeller/wiki
Author-email: Алексей Устинов <lesin2798@mail.ru>
License-Expression: MIT
License-File: LICENSE
Keywords: api,speller,yandex
Classifier: License :: OSI Approved :: MIT License
Classifier: Operating System :: OS Independent
Classifier: Programming Language :: Python :: 3
Requires-Python: >=3.12
